langchain_nvidia.py
langchain_nvidia_ai_endpoints/__init__.py
langchain_nvidia_ai_endpoints/_common.py
langchain_nvidia_ai_endpoints/_statics.py
langchain_nvidia_ai_endpoints/_utils.py
langchain_nvidia_ai_endpoints/callbacks.py
langchain_nvidia_ai_endpoints/chat_models.py
langchain_nvidia_ai_endpoints/embeddings.py
langchain_nvidia_ai_endpoints/llm.py
langchain_nvidia_ai_endpoints/py.typed
langchain_nvidia_ai_endpoints/reranking.py
langchain_nvidia_ai_endpoints-1.0.2.dist-info/LICENSE
langchain_nvidia_ai_endpoints-1.0.2.dist-info/METADATA
langchain_nvidia_ai_endpoints-1.0.2.dist-info/WHEEL
langchain_nvidia_ai_endpoints-1.0.2.dist-info/RECORD
