Metadata-Version: 2.1
Name: langchain-nvidia-ai-endpoints
Version: 1.0.2
Summary: An integration package connecting NVIDIA AI Endpoints and LangChain
Home-page: https://github.com/langchain-ai/langchain-nvidia
License: MIT
Requires-Python: >=3.10.0,<4.0.0
Classifier: License :: OSI Approved :: MIT License
Classifier: Programming Language :: Python :: 3
Classifier: Programming Language :: Python :: 3.10
Classifier: Programming Language :: Python :: 3.11
Classifier: Programming Language :: Python :: 3.12
Requires-Dist: aiohttp (>=3.9.1,<4.0.0)
Requires-Dist: filetype (>=1.2.0,<2.0.0)
Requires-Dist: langchain-core (>=1.0.0,<2.0.0)
Project-URL: Repository, https://github.com/langchain-ai/langchain-nvidia
Project-URL: Source Code, https://github.com/langchain-ai/langchain-nvidia/tree/main/libs/ai-endpoints
